{"cameraMode":{"drawMode":0,"name":"Shaded","section":"Shading Mode"},"sceneLighting":true,"audioPlay":false,"sceneViewState":{"showFog":true,"showMaterialUpdate":false,"showSkybox":true,"showFlares":true,"showImageEffects":true,"showParticleSystems":true},"in2DMode":false,"pivot":{"x":408.67022705078127,"y":396.46124267578127,"z":389.9437255859375},"rotation":{"x":-0.23844602704048158,"y":-0.0892692506313324,"z":0.022072158753871919,"w":-0.9668179750442505},"size":292.1085205078125,"orthographic":false}